lyricsprocessor/__init__.py
lyricsprocessor/lyrics_generation_script.py
lyricsprocessor/fetch_lyrics/__init__.py
lyricsprocessor/fetch_lyrics/fetch_lyrics.py
lyricsprocessor/process_lyrics/__init__.py
lyricsprocessor/process_lyrics/process_lyrics.py
lyricsprocessor/utils/__init__.py
lyricsprocessor/utils/utils.py
lyricsprocessor/write_lyrics_to_file/__init__.py
lyricsprocessor/write_lyrics_to_file/write_lyrics_to_file.py
lyricsprocessor-0.1.18.dist-info/LICENSE
lyricsprocessor-0.1.18.dist-info/METADATA
lyricsprocessor-0.1.18.dist-info/WHEEL
lyricsprocessor-0.1.18.dist-info/top_level.txt
lyricsprocessor-0.1.18.dist-info/RECORD
