Metadata-Version: 2.1
Name: lyricsprocessor
Version: 0.1.18
Summary: Lyrics processing code
Home-page: https://github.com/Mitchwatts93/lyrics_generator
Author: https://github.com/Mitchwatts93
Author-email: 
License: MIT
Keywords: lyricsgenius genius lyrics
Platform: UNKNOWN
Classifier: Programming Language :: Python :: 3.7
Classifier: License :: OSI Approved :: MIT License
Classifier: Operating System :: OS Independent
Requires-Python: >=3.7
Requires-Dist: pandas (>=0.23.4)
Requires-Dist: argparse (>=1.1)
Requires-Dist: lyricsgenius (>=1.8.0)
